Workbook

Sheet Summary
A1: Collection delay changes temporary cash needs
A2: Synthetic cash timing only / SCU is not a real currency
A3: Scenario | B3: Lag (periods) | C3: Total billings | D3: Cash trough | E3: Funding need | F3: Assumed buffer | G3: Unfunded gap | H3: Ending receivables
A4: =Inputs!A9 -> Scenario: no lag | B4: =Inputs!B9 -> 0 | C4: =SUM('Cash bridges'!C4:C7) -> 400 | D4: =MIN(Inputs!B4,'Cash bridges'!G4:G7) -> 0 | E4: =MAX(0,-D4) -> 0 | F4: =Inputs!B7 -> 75 | G4: =MAX(0,E4-F4) -> 0 | H4: =C4-SUM('Cash bridges'!D4:D7) -> 0
A5: =Inputs!A10 -> Scenario: one-period lag | B5: =Inputs!B10 -> 1 | C5: =SUM('Cash bridges'!C9:C12) -> 400 | D5: =MIN(Inputs!B4,'Cash bridges'!G9:G12) -> -60 | E5: =MAX(0,-D5) -> 60 | F5: =Inputs!B7 -> 75 | G5: =MAX(0,E5-F5) -> 0 | H5: =C5-SUM('Cash bridges'!D9:D12) -> 100
A6: =Inputs!A11 -> Scenario: two-period lag | B6: =Inputs!B11 -> 2 | C6: =SUM('Cash bridges'!C14:C17) -> 400 | D6: =MIN(Inputs!B4,'Cash bridges'!G14:G17) -> -120 | E6: =MAX(0,-D6) -> 120 | F6: =Inputs!B7 -> 75 | G6: =MAX(0,E6-F6) -> 45 | H6: =C6-SUM('Cash bridges'!D14:D17) -> 200
A7: SYNTHETIC ONLY / Arithmetic illustration; see Inputs for scope limits.

Sheet Inputs
A1: Synthetic collection-timing inputs
A2: Field | B2: Value | C2: Unit / boundary
A3: Periods | B3: 4 | C3: periods
A4: Opening cash | B4: 0 | C4: SCU
A5: Monthly billings | B5: 100 | C5: SCU/period
A6: Monthly cash costs | B6: 60 | C6: SCU/period
A7: Available liquidity | B7: 75 | C7: SCU; assumed buffer, not committed funding
A8: Collection rate | B8: 100 | C8: %; simplified test assumption
A9: Scenario: no lag | B9: 0 | C9: periods
A10: Scenario: one-period lag | B10: 1 | C10: periods
A11: Scenario: two-period lag | B11: 2 | C11: periods
A12: Scope | B12: SYNTHETIC ONLY | C12: No client, market, tax or accounting conclusion.
A13: Source | B13: P13-SYNTHETIC-CASH-TIMING-FIXTURE | C13: Values reproduce the bounded P13 synthetic fixture for document-format testing; no customer, market or accounting source was supplied.

Sheet Cash bridges
A1: Monthly cash bridge by synthetic collection lag
A2: Scenario | B2: Period | C2: Billings | D2: Cash receipts | E2: Cash costs | F2: Opening cash | G2: Closing cash | H2: Collection lag
A4: =Inputs!A9 -> Scenario: no lag | B4: 1 | C4: =Inputs!B5 -> 100 | D4: =IF(B4>Inputs!B9,C4,0) -> 100 | E4: =Inputs!B6 -> 60 | F4: =Inputs!B4 -> 0 | G4: =F4+D4-E4 -> 40 | H4: =Inputs!B9 -> 0
A5: =Inputs!A9 -> Scenario: no lag | B5: 2 | C5: =Inputs!B5 -> 100 | D5: =IF(B5>Inputs!B9,C5,0) -> 100 | E5: =Inputs!B6 -> 60 | F5: =G4 -> 40 | G5: =F5+D5-E5 -> 80 | H5: =Inputs!B9 -> 0
A6: =Inputs!A9 -> Scenario: no lag | B6: 3 | C6: =Inputs!B5 -> 100 | D6: =IF(B6>Inputs!B9,C6,0) -> 100 | E6: =Inputs!B6 -> 60 | F6: =G5 -> 80 | G6: =F6+D6-E6 -> 120 | H6: =Inputs!B9 -> 0
A7: =Inputs!A9 -> Scenario: no lag | B7: 4 | C7: =Inputs!B5 -> 100 | D7: =IF(B7>Inputs!B9,C7,0) -> 100 | E7: =Inputs!B6 -> 60 | F7: =G6 -> 120 | G7: =F7+D7-E7 -> 160 | H7: =Inputs!B9 -> 0
A9: =Inputs!A10 -> Scenario: one-period lag | B9: 1 | C9: =Inputs!B5 -> 100 | D9: =IF(B9>Inputs!B10,C9,0) -> 0 | E9: =Inputs!B6 -> 60 | F9: =Inputs!B4 -> 0 | G9: =F9+D9-E9 -> -60 | H9: =Inputs!B10 -> 1
A10: =Inputs!A10 -> Scenario: one-period lag | B10: 2 | C10: =Inputs!B5 -> 100 | D10: =IF(B10>Inputs!B10,C10,0) -> 100 | E10: =Inputs!B6 -> 60 | F10: =G9 -> -60 | G10: =F10+D10-E10 -> -20 | H10: =Inputs!B10 -> 1
A11: =Inputs!A10 -> Scenario: one-period lag | B11: 3 | C11: =Inputs!B5 -> 100 | D11: =IF(B11>Inputs!B10,C11,0) -> 100 | E11: =Inputs!B6 -> 60 | F11: =G10 -> -20 | G11: =F11+D11-E11 -> 20 | H11: =Inputs!B10 -> 1
A12: =Inputs!A10 -> Scenario: one-period lag | B12: 4 | C12: =Inputs!B5 -> 100 | D12: =IF(B12>Inputs!B10,C12,0) -> 100 | E12: =Inputs!B6 -> 60 | F12: =G11 -> 20 | G12: =F12+D12-E12 -> 60 | H12: =Inputs!B10 -> 1
A14: =Inputs!A11 -> Scenario: two-period lag | B14: 1 | C14: =Inputs!B5 -> 100 | D14: =IF(B14>Inputs!B11,C14,0) -> 0 | E14: =Inputs!B6 -> 60 | F14: =Inputs!B4 -> 0 | G14: =F14+D14-E14 -> -60 | H14: =Inputs!B11 -> 2
A15: =Inputs!A11 -> Scenario: two-period lag | B15: 2 | C15: =Inputs!B5 -> 100 | D15: =IF(B15>Inputs!B11,C15,0) -> 0 | E15: =Inputs!B6 -> 60 | F15: =G14 -> -60 | G15: =F15+D15-E15 -> -120 | H15: =Inputs!B11 -> 2
A16: =Inputs!A11 -> Scenario: two-period lag | B16: 3 | C16: =Inputs!B5 -> 100 | D16: =IF(B16>Inputs!B11,C16,0) -> 100 | E16: =Inputs!B6 -> 60 | F16: =G15 -> -120 | G16: =F16+D16-E16 -> -80 | H16: =Inputs!B11 -> 2
A17: =Inputs!A11 -> Scenario: two-period lag | B17: 4 | C17: =Inputs!B5 -> 100 | D17: =IF(B17>Inputs!B11,C17,0) -> 100 | E17: =Inputs!B6 -> 60 | F17: =G16 -> -80 | G17: =F17+D17-E17 -> -40 | H17: =Inputs!B11 -> 2

Sheet Chart data
A1: Gap comparison for the summary chart
A3: Collection delay | B3: Unfunded gap (SCU)
A4: No lag | B4: =Summary!G4 -> 0
A5: One-period lag | B5: =Summary!G5 -> 0
A6: Two-period lag | B6: =Summary!G6 -> 45
